README.rst
setup.cfg
setup.py
pordego_dependency/__init__.py
pordego_dependency/analysis_result.py
pordego_dependency/analyzer.py
pordego_dependency/dependency_analysis.py
pordego_dependency/dependency_config.py
pordego_dependency/dependency_tools.py
pordego_dependency/entry_point.py
pordego_dependency/requirement_resolver.py
pordego_dependency/requirements_analysis.py
pordego_dependency/snakefood_lib.py
pordego_dependency3.egg-info/PKG-INFO
pordego_dependency3.egg-info/SOURCES.txt
pordego_dependency3.egg-info/dependency_links.txt
pordego_dependency3.egg-info/entry_points.txt
pordego_dependency3.egg-info/requires.txt
pordego_dependency3.egg-info/top_level.txt