Metadata-Version: 2.1
Name: pordego-dependency3
Version: 1.2.2
Summary: Pordego plugin for code complexity analysis using the snakefood library
Home-page: https://github.com/sanvyruz/pordego-dependency
Author: Sandeep Cavale
Author-email: sandeepcavale@gmail.com
License: GPLv2
Download-URL: https://github.com/sanvyruz/pordego-dependency/tarball/1.2.2
Platform: UNKNOWN
Classifier: Development Status :: 4 - Beta
Classifier: Intended Audience :: Developers
Classifier: License :: OSI Approved :: GNU General Public License v2 (GPLv2)
Classifier: Operating System :: OS Independent
Classifier: Programming Language :: Python
Classifier: Programming Language :: Python :: 2.7
Classifier: Programming Language :: Python :: 3.6
Classifier: Programming Language :: Python :: 3.7
